[
  {
    "id": "emmas-corruption",
    "title": "Emma's Corruption",
    "author": "Antalore42",
    "categories": [
      "3D",
      "Adulte"
    ],
    "description": "L'histoire d'Emma et son chemin vers la corruption",
    "cover_image": "https://res.cloudinary.com/dh8f5kqra/image/upload/v1746157820/mesBD/Categorie/3D/Antalore42%20Emma%27s%20Corruption/Chapitre%2001/01-001.jpg",
    "created_at": "2025-01-15"
  },
  {
    "id": "the-new-neighbors",
    "title": "The New Neighbors",
    "author": "Antalore42",
    "categories": [
      "3D",
      "Aventure"
    ],
    "description": "Une histoire de nouveaux voisins et leurs découvertes",
    "cover_image": "https://res.cloudinary.com/dh8f5kqra/image/upload/v1746157969/mesBD/Categorie/3D/Antalore42%20The%20New%20Neighbors/Chapitre%2001/01-001.jpg",
    "created_at": "2025-02-10"
  },
  {
    "id": "caroline",
    "title": "Caroline",
    "author": "CrazyDad3D",
    "categories": [
      "3D",
      "Adulte",
      "Romance"
    ],
    "description": "L'histoire captivante de Caroline dans un monde plein de mystères et de découvertes",
    "cover_image": "https://res.cloudinary.com/dh8f5kqra/image/upload/v1746236406/mesBD/Categorie/3D/CrazyDad3D%20Caroline/Chapitre%2001/01-001.jpg",
    "created_at": "2025-05-03"
  },
  {
    "id": "clarice",
    "title": "Clarice",
    "author": "CrazyDad3D",
    "categories": [
      "3D"
    ],
    "description": "L'histoire captivante de Clarice",
    "cover_image": "https://res.cloudinary.com/dh8f5kqra/image/upload/v1746237017/mesBD/Categorie/3D/CrazyDad3D%20Clarice/Chapitre%2001/01-001.jpg",
    "created_at": "2025/05/03"
  },
  {
    "id": "daddy-crazy-desire",
    "title": "Daddy, Crazy Desire",
    "author": "CrazyDad3D",
    "categories": [
      "3D"
    ],
    "description": "L'histoire captivante de Daddy, Crazy Desire",
    "cover_image": "https://res.cloudinary.com/dh8f5kqra/image/upload/v1746237552/mesBD/Categorie/3D/CrazyDad3D%20Daddy%2C%20Crazy%20Desire/Chapitre%2001/01-001.jpg",
    "created_at": "2025/05/03"
  },
  {
    "id": "dear-older-sister",
    "title": "Dear Older Sister",
    "author": "CrazyDad3D",
    "categories": [
      "3D"
    ],
    "description": "L'histoire captivante de Dear Older Sister",
    "cover_image": "https://res.cloudinary.com/dh8f5kqra/image/upload/v1746237927/mesBD/Categorie/3D/CrazyDad3D%20Dear%20Older%20Sister/Chapitre%2001/01-001.jpg",
    "created_at": "2025/05/03"
  },
  {
    "id": "doctor-brandie",
    "title": "Doctor Brandie",
    "author": "CrazyDad3D",
    "categories": [
      "3D"
    ],
    "description": "L'histoire captivante de Doctor Brandie",
    "cover_image": "https://res.cloudinary.com/dh8f5kqra/image/upload/v1746238373/mesBD/Categorie/3D/CrazyDad3D%20Doctor%20Brandie/Chapitre%2001/01-001.jpg",
    "created_at": "2025/05/03"
  },
  {
    "id": "family-sins",
    "title": "Family Sins",
    "author": "CrazyDad3D",
    "categories": [
      "3D"
    ],
    "description": "L'histoire captivante de Family Sins",
    "cover_image": "https://res.cloudinary.com/dh8f5kqra/image/upload/v1746423608/mesBD/Categorie/3D/CrazyDad3D%20Family%20Sins/Chapitre%2001/01-001.jpg",
    "created_at": "2025-05-06"
  },
  {
    "id": "forbidden-love",
    "title": "Forbidden Love",
    "author": "CrazyDad3D",
    "categories": [
      "3D"
    ],
    "description": "L'histoire captivante de Forbidden Love",
    "cover_image": "https://res.cloudinary.com/dh8f5kqra/image/upload/v1746423672/mesBD/Categorie/3D/CrazyDad3D%20Forbidden%20Love/Chapitre%2001/01-001.jpg",
    "created_at": "2025-05-06"
  },
  {
    "id": "madison",
    "title": "Madison",
    "author": "CrazyDad3D",
    "categories": [
      "3D"
    ],
    "description": "L'histoire captivante de Madison",
    "cover_image": "https://res.cloudinary.com/dh8f5kqra/image/upload/v1746423760/mesBD/Categorie/3D/CrazyDad3D%20Madison/Chapitre%2001/01-001.jpg",
    "created_at": "2025-05-06"
  },
  {
    "id": "the-shepherd-s-wife",
    "title": "The Shepherd's Wife",
    "author": "CrazyDad3D",
    "categories": [
      "3D"
    ],
    "description": "L'histoire captivante de The Shepherd's Wife",
    "cover_image": "https://res.cloudinary.com/dh8f5kqra/image/upload/v1746423910/mesBD/Categorie/3D/CrazyDad3D%20The%20Shepherd%27s%20Wife/Chapitre%2001/01-001.jpg",
    "created_at": "2025-05-06"
  },
  {
    "id": "turner-family",
    "title": "Turner Family",
    "author": "CrazyDad3D",
    "categories": [
      "3D"
    ],
    "description": "L'histoire captivante de Turner Family",
    "cover_image": "https://res.cloudinary.com/dh8f5kqra/image/upload/v1746424045/mesBD/Categorie/3D/CrazyDad3D%20Turner%20Family/Chapitre%2001/01-001.jpg",
    "created_at": "2025-05-06"
  },
  {
    "id": "smith-timmy-strikes-back",
    "title": "Smith Timmy Strikes Back",
    "author": "Pegasus",
    "categories": [
      "3D"
    ],
    "description": "L'histoire captivante de Smith Timmy Strikes Back",
    "cover_image": "https://res.cloudinary.com/dh8f5kqra/image/upload/v1746424164/mesBD/Categorie/3D/Pegasus%20Smith%20Timmy%20Strikes%20Back/Chapitre%2001/001.jpg",
    "created_at": "2025-05-06"
  },
  {
    "id": "emma-s-corruption",
    "title": "Emma's Corruption",
    "author": "Antalore42",
    "categories": [
      "3D"
    ],
    "description": "L'histoire captivante de Emma's Corruption",
    "cover_image": "https://res.cloudinary.com/dh8f5kqra/image/upload/v1746157820/mesBD/Categorie/3D/Antalore42%20Emma%27s%20Corruption/Chapitre%2001/01-001.jpg",
    "created_at": "2025-05-08"
  },
  {
    "id": "shoes-c-s-b-w",
    "title": "Shoes C.S.B.W",
    "author": "Brown",
    "categories": [
      "3D"
    ],
    "description": "L'histoire captivante de Shoes C.S.B.W",
    "cover_image": "https://res.cloudinary.com/dh8f5kqra/image/upload/v1746507081/mesBD/Categorie/3D/Brown%20Shoes%20C.S.B.W/chapitre%2001/01-001.jpg",
    "created_at": "2025-05-08"
  },
  {
    "id": "sister-grace",
    "title": "Sister Grace",
    "author": "CrazyDad3D",
    "categories": [
      "3D"
    ],
    "description": "L'histoire captivante de Sister Grace",
    "cover_image": "https://res.cloudinary.com/dh8f5kqra/image/upload/v1746507203/mesBD/Categorie/3D/CrazyDad3D%20Sister%20Grace/Chapitre%2001/0101.jpg",
    "created_at": "2025-05-08"
  },
  {
    "id": "white-nun",
    "title": "White Nun",
    "author": "CrazyDad3D",
    "categories": [
      "3D"
    ],
    "description": "L'histoire captivante de White Nun",
    "cover_image": "https://res.cloudinary.com/dh8f5kqra/image/upload/v1746507267/mesBD/Categorie/3D/CrazyDad3D%20White%20Nun/Chapitre%2001/White%20Nun%201%2001.jpg",
    "created_at": "2025-05-08"
  },
  {
    "id": "immoral-desires",
    "title": "Immoral Desires",
    "author": "Daval3D",
    "categories": [
      "3D"
    ],
    "description": "L'histoire captivante de Immoral Desires",
    "cover_image": "https://res.cloudinary.com/dh8f5kqra/image/upload/v1746507351/mesBD/Categorie/3D/Daval3D%20Immoral%20Desires/Chapitre%2001/000.jpg",
    "created_at": "2025-05-08"
  },
  {
    "id": "satisfying-needs",
    "title": "Satisfying Needs",
    "author": "Daval3D",
    "categories": [
      "3D"
    ],
    "description": "L'histoire captivante de Satisfying Needs",
    "cover_image": "https://res.cloudinary.com/dh8f5kqra/image/upload/v1746507524/mesBD/Categorie/3D/Daval3D%20Satisfying%20Needs/Chapitre%2001/01-001.jpg",
    "created_at": "2025-05-08"
  },
  {
    "id": "sandy-planet",
    "title": "Sandy Planet",
    "author": "Goldenmaster",
    "categories": [
      "3D"
    ],
    "description": "L'histoire captivante de Sandy Planet",
    "cover_image": "https://res.cloudinary.com/dh8f5kqra/image/upload/v1746507654/mesBD/Categorie/3D/Goldenmaster%20Sandy%20Planet/Chapitre%2002/02-000.jpg",
    "created_at": "2025-05-08"
  },
  {
    "id": "neighbors",
    "title": "Neighbors",
    "author": "Morpheuscuk",
    "categories": [
      "3D"
    ],
    "description": "L'histoire captivante de Neighbors",
    "cover_image": "https://res.cloudinary.com/dh8f5kqra/image/upload/v1746507915/mesBD/Categorie/3D/Morpheuscuk%20Neighbors/Chapitre%2001/01-001.jpg",
    "created_at": "2025-05-08"
  },
  {
    "id": "shoes-the-fall-of-the-elf-queen",
    "title": "Shoes] The Fall of the Elf Queen",
    "author": "[Brown",
    "categories": [
      "3D"
    ],
    "description": "L'histoire captivante de Shoes] The Fall of the Elf Queen",
    "cover_image": "https://res.cloudinary.com/dh8f5kqra/image/upload/v1746508268/mesBD/Categorie/3D/%5BBrown%20Shoes%5D%20The%20Fall%20of%20the%20Elf%20Queen/Chapitre%2001/01-001.jpg",
    "created_at": "2025-05-08"
  },
  {
    "id": "grey-the-stay",
    "title": "Grey] The Stay",
    "author": "[Dirk",
    "categories": [
      "3D"
    ],
    "description": "L'histoire captivante de Grey] The Stay",
    "cover_image": "https://res.cloudinary.com/dh8f5kqra/image/upload/v1746508333/mesBD/Categorie/3D/%5BDirk%20Grey%5D%20The%20Stay/Chapitre%2001/01-001.jpg",
    "created_at": "2025-05-08"
  },
  {
    "id": "the-maid",
    "title": "The Maid",
    "author": "[Gonzales]",
    "categories": [
      "3D"
    ],
    "description": "L'histoire captivante de The Maid",
    "cover_image": "https://res.cloudinary.com/dh8f5kqra/image/upload/v1746508511/mesBD/Categorie/3D/%5BGonzales%5D%20The%20Maid/Chapitre%2001/01-000.jpg",
    "created_at": "2025-05-08"
  },
  {
    "id": "royal-slaves-of-the-orc-kingdom",
    "title": "Royal Slaves of the Orc Kingdom",
    "author": "[MercyMagnet]",
    "categories": [
      "3D"
    ],
    "description": "L'histoire captivante de Royal Slaves of the Orc Kingdom",
    "cover_image": "https://res.cloudinary.com/dh8f5kqra/image/upload/v1746508534/mesBD/Categorie/3D/%5BMercyMagnet%5D%20Royal%20Slaves%20of%20the%20Orc%20Kingdom/Chapitre%2001/01-001.jpg",
    "created_at": "2025-05-08"
  }
]